einit/__init__.py
einit/einit.py
einit-0.1.0.dist-info/licenses/LICENSE
tests/__init__.py
tests/test_einit.py
tests/test_integration.py
tests/visualize_failures.py
einit-0.1.0.dist-info/METADATA
einit-0.1.0.dist-info/WHEEL
einit-0.1.0.dist-info/top_level.txt
einit-0.1.0.dist-info/RECORD
